minimal_ecash_sender/__init__.py
minimal_ecash_sender/cli.py
minimal_ecash_sender/core.py
minimal_ecash_sender-1.0.0.dist-info/licenses/LICENSE
minimal_ecash_sender-1.0.0.dist-info/METADATA
minimal_ecash_sender-1.0.0.dist-info/WHEEL
minimal_ecash_sender-1.0.0.dist-info/entry_points.txt
minimal_ecash_sender-1.0.0.dist-info/top_level.txt
minimal_ecash_sender-1.0.0.dist-info/RECORD
