Metadata-Version: 2.4
Name: minimal-ecash-sender
Version: 1.0.0
Summary: Minimal eCash (XEC) Electrum ABC/Fulcrum client: build, sign, and broadcast P2PKH transactions from a wallet with BIP39 mnemonic.
Author-email: xecdev <ecashinformer@gmail.com>
License: MIT License
Project-URL: Homepage, https://github.com/xecdev/minimal-ecash-sender
Project-URL: Issues, https://github.com/xecdev/minimal-ecash-sender/issues
Classifier: Programming Language :: Python :: 3
Classifier: License :: OSI Approved :: MIT License
Classifier: Operating System :: OS Independent
Classifier: Topic :: Internet
Classifier: Topic :: Security :: Cryptography
Requires-Python: >=3.8
License-File: LICENSE
Requires-Dist: bip-utils>=2.9.3
Requires-Dist: ecdsa>=0.18.0
Requires-Dist: ecashaddress>=1.0.2
Requires-Dist: base58>=2.1.1
Dynamic: license-file
